[
    {
        "skillIndex": "0",
        "skillName": "공격속도 강화",
        "codeName": "attackspeedBuff",
        "skillLevel": "1",
        "skillValue": "10",
        "secondValue": "5",
        "coolTime": "30",
        "flavorText": "공격속도를 증가시켜 줍니다.",
        "skillType": "buff",
        "OffenceSkillType": "none",
        "OffenceRangeType": "none",
        "DeffenceSkillType": "none",
        "BuffSkillType": "attackSpeed"
    },
    {
        "skillIndex": "1",
        "skillName": "이동속도 강화",
        "codeName": "speedBuff",
        "skillLevel": "1",
        "skillValue": "10",
        "secondValue": "5",
        "coolTime": "30",
        "flavorText": "이동속도를 증가시켜 줍니다.",
        "skillType": "buff",
        "OffenceSkillType": "none",
        "OffenceRangeType": "none",
        "DeffenceSkillType": "none",
        "BuffSkillType": "moveSpeed"
    },
    {
        "skillIndex": "2",
        "skillName": "치명타데미지 강화",
        "codeName": "criticaldamageBuff",
        "skillLevel": "1",
        "skillValue": "20",
        "secondValue": "5",
        "coolTime": "300",
        "flavorText": "치명타 데미지를 증가시켜 줍니다.",
        "skillType": "buff",
        "OffenceSkillType": "none",
        "OffenceRangeType": "none",
        "DeffenceSkillType": "none",
        "BuffSkillType": "criticalDamage"
    },
    {
        "skillIndex": "3",
        "skillName": "대쉬",
        "codeName": "activeDash",
        "skillLevel": "1",
        "skillValue": "10",
        "secondValue": "0.4",
        "coolTime": "4",
        "flavorText": "전방을 향해 빠르게 접근 합니다.",
        "skillType": "deffence",
        "OffenceSkillType": "none",
        "OffenceRangeType": "none",
        "DeffenceSkillType": "dodge",
        "BuffSkillType": "none"
    },
    {
        "skillIndex": "4",
        "skillName": "체력회복",
        "codeName": "activeHeal",
        "skillLevel": "1",
        "skillValue": "60",
        "secondValue": "0",
        "coolTime": "20",
        "flavorText": "플레이어의 체력을 즉시 회복합니다.",
        "skillType": "buff",
        "OffenceSkillType": "none",
        "OffenceRangeType": "none",
        "DeffenceSkillType": "deffence",
        "BuffSkillType": "none"
    }
]